odoo/addons/sale_order_lot_selection_by_quant/README.rst
odoo/addons/sale_order_lot_selection_by_quant/__init__.py
odoo/addons/sale_order_lot_selection_by_quant/__manifest__.py
odoo/addons/sale_order_lot_selection_by_quant/i18n/it.po
odoo/addons/sale_order_lot_selection_by_quant/i18n/sale_order_lot_selection_by_quant.pot
odoo/addons/sale_order_lot_selection_by_quant/readme/CONTRIBUTORS.rst
odoo/addons/sale_order_lot_selection_by_quant/readme/DESCRIPTION.rst
odoo/addons/sale_order_lot_selection_by_quant/readme/USAGE.rst
odoo/addons/sale_order_lot_selection_by_quant/static/description/icon.png
odoo/addons/sale_order_lot_selection_by_quant/static/description/index.html
odoo/addons/sale_order_lot_selection_by_quant/static/description/img/quant_selection_popup.png
odoo/addons/sale_order_lot_selection_by_quant/static/description/img/sol_magnifying_glass.png
odoo/addons/sale_order_lot_selection_by_quant/static/src/js/quant_list_controller.js
odoo/addons/sale_order_lot_selection_by_quant/static/src/js/sale_order_quant_list_view.js
odoo/addons/sale_order_lot_selection_by_quant/static/src/js/select_lot_by_quant_widget.js
odoo/addons/sale_order_lot_selection_by_quant/static/src/scss/select_lot_by_quant_widget.scss
odoo/addons/sale_order_lot_selection_by_quant/static/tests/tours/so_lot_selection_by_quant_tour.js
odoo/addons/sale_order_lot_selection_by_quant/tests/__init__.py
odoo/addons/sale_order_lot_selection_by_quant/tests/test_sale_order_lot_selection_by_quant.py
odoo/addons/sale_order_lot_selection_by_quant/view/assets.xml
odoo/addons/sale_order_lot_selection_by_quant/view/sale_view.xml
odoo/addons/sale_order_lot_selection_by_quant/view/stock_quant_view.xml
odoo14_addon_sale_order_lot_selection_by_quant-14.0.1.0.1.dist-info/METADATA
odoo14_addon_sale_order_lot_selection_by_quant-14.0.1.0.1.dist-info/WHEEL
odoo14_addon_sale_order_lot_selection_by_quant-14.0.1.0.1.dist-info/top_level.txt
odoo14_addon_sale_order_lot_selection_by_quant-14.0.1.0.1.dist-info/RECORD
